vietnam_provinces/__init__.py
vietnam_provinces/base.py
vietnam_provinces/codes.py
vietnam_provinces/compat.py
vietnam_provinces/lookup.py
vietnam_provinces/py.typed
vietnam_provinces/data/flat-divisions.json
vietnam_provinces/data/nested-divisions.json
vietnam_provinces-2026.1.0.dist-info/WHEEL
vietnam_provinces-2026.1.0.dist-info/METADATA
vietnam_provinces-2026.1.0.dist-info/RECORD
