Metadata-Version: 2.4
Name: vietnam-provinces
Version: 2026.1.0
Summary: Library to provide list of Vietnam administrative divisions (tỉnh thành, quận huyện, phường xã).
Keywords: Vietnam,administrative,division,locality
Author-email: Nguyễn Hồng Quân <ng.hong.quan@gmail.com>
Requires-Python: <4.0,>=3.12
Classifier: Natural Language :: Vietnamese
Classifier: Intended Audience :: Information Technology
Classifier: Intended Audience :: Financial and Insurance Industry
Classifier: Intended Audience :: Telecommunications Industry
Classifier: Operating System :: OS Independent
Classifier: Topic :: Software Development :: Localization
Classifier: Programming Language :: Python :: 3 :: Only
Classifier: Topic :: Software Development :: Libraries :: Python Modules
Classifier: Development Status :: 4 - Beta
Classifier: Intended Audience :: Developers
Requires-Dist: multidict>=6.7.0
Project-URL: Changelog, https://github.com/sunshine-tech/VietnamProvinces/blob/main/CHANGELOG.md
Project-URL: Documentation, https://vietnamprovinces.readthedocs.io
Project-URL: Homepage, https://github.com/sunshine-tech/VietnamProvinces
Project-URL: Repository, https://github.com/sunshine-tech/VietnamProvinces.git
